Workbook

Sheet README
A1: Using Decision Support Systems to Make a Business Decision
A3: Scenario selected | B3: New Store Location Selection
A4: Decision question | B4: Which of three potential locations should the company open next?
A5: Recommendation | B5: Open the SouthSide location.
A6: Primary decision metric | B6: 3-year NPV plus weighted decision score
A7: DSS techniques included | B7: Data tables, visualization, scenario evaluation, scenario-manager style selector, and Goal Seek/Solver-style optimization.
A8: Workbook structure | B8: Inputs, Location_Data, Scenario_Manager, Goal_Seek_Solver, Dashboard
A9: Prepared for | B9: Management decision support
A10: Prepared by | B10: Juan Barrera
A11: Date | B11: 46195
A12: Note | B12: Financial inputs are internally modeled assumptions for an academic DSS exercise; replace assumptions with verified company data before investing.

Sheet Inputs
A1: Model Inputs and Decision Weights
A3: Model assumption | B3: Value | C3: Notes | E3: Weighted score factor | F3: Weight | G3: Rationale
A4: Discount rate | B4: 0.1 | C4: Used in 3-year NPV | E4: Profit potential | F4: 0.3 | G4: Most direct contributor to growth
A5: Population demand factor | B5: 0.004 | C5: Monthly customer contribution per person within 3 miles | E5: Revenue upside | F5: 0.2 | G5: Measures demand and sales opportunity
A6: Traffic conversion multiplier | B6: 1.6 | C6: Expected-case uplift applied to base conversion rate | E6: Rent efficiency | F6: 0.15 | G6: Lower fixed costs reduce break-even pressure
A7: Competition penalty | B7: 0.06 | C7: Demand penalty per nearby competitor | E7: Traffic access | F7: 0.15 | G7: Higher visibility improves acquisition
A8: Planning horizon | B8: 3 | C8: Years | E8: Competitive intensity | F8: 0.1 | G8: Lower competition lowers demand leakage
A9: Service capacity per employee | B9: 250 | C9: Monthly customers handled per employee | E9: Population density | F9: 0.1 | G9: Larger nearby market supports repeat visits
A10: Monthly cost per employee | B10: 1500 | C10: Wages, taxes, benefits, and scheduling coverage | E10: Total | F10: 1 | G10: Weights sum to 100%

Sheet Location_Data
A1: Location Comparison Model
A3: Location | B3: Monthly Rent | C3: Population (3 mi) | D3: Avg Daily Traffic | E3: Competitors | F3: Opening Cost | G3: Avg Ticket | H3: Gross Margin | I3: Base Conversion | J3: Staffing Cost | K3: Other Fixed Cost | L3: Marketing Cost | M3: Comp. Adj. | N3: Projected Customers | O3: Revenue | P3: Gross Profit | Q3: Total Op. Cost | R3: Monthly Profit | S3: Annual Profit | T3: 3-Year NPV | U3: Weighted Score
A4: Downtown/CBD | B4: 18000 | C4: 95000 | D4: 23000 | E4: 12 | F4: 220000 | G4: 24 | H4: 0.58 | I4: 0.0075 | J4: 42000 | K4: 13000 | L4: 5500 | M4: =1/(1+E4*Inputs!$B$7) -> 0.58139535 | N4: =(C4*Inputs!$B$5 + D4*30*I4*Inputs!$B$6)*M4 -> 5034.8837 | O4: =N4*G4 -> 120837.21 | P4: =O4*H4 -> 70085.581 | Q4: =B4+J4+K4+L4 -> 78500 | R4: =P4-Q4 -> -8414.4186 | S4: =R4*12 -> -100973.02 | T4: =-F4+S4/(1+Inputs!$B$4)+S4/(1+Inputs!$B$4)^2+S4/(1+Inputs!$B$4)^3 -> -471104.96 | U4: =100*(Inputs!$F$4*((R4-MIN($R$4:$R$6))/(MAX($R$4:$R$6)-MIN($R$4:$R$6)))+Inputs!$F$5*((O4-MIN($O$4:$O$6))/(MAX($O$4:$O$6)-MIN($O$4:$O$6)))+Inputs!$F$6*((MAX($B$4:$B$6)-B4)/(MAX($B$4:$B$6)-MIN($B$4:$B$6)))+Inputs!$F$7*((D4-MIN($D$4:$D$6))/(MAX($D$4:$D$6)-MIN($D$4:$D$6)))+Inputs!$F$8*((MAX($E$4:$E$6)-E4)/(MAX($E$4:$E$6)-MIN($E$4:$E$6)))+Inputs!$F$9*((C4-MIN($C$4:$C$6))/(MAX($C$4:$C$6)-MIN($C$4:$C$6)))) -> 37.220671
A5: Oakland/University | B5: 13500 | C5: 118000 | D5: 18000 | E5: 8 | F5: 185000 | G5: 22 | H5: 0.6 | I5: 0.0085 | J5: 36000 | K5: 10000 | L5: 5000 | M5: =1/(1+E5*Inputs!$B$7) -> 0.67567568 | N5: =(C5*Inputs!$B$5 + D5*30*I5*Inputs!$B$6)*M5 -> 5281.0811 | O5: =N5*G5 -> 116183.78 | P5: =O5*H5 -> 69710.27 | Q5: =B5+J5+K5+L5 -> 64500 | R5: =P5-Q5 -> 5210.2703 | S5: =R5*12 -> 62523.243 | T5: =-F5+S5/(1+Inputs!$B$4)+S5/(1+Inputs!$B$4)^2+S5/(1+Inputs!$B$4)^3 -> -29513.948 | U5: =100*(Inputs!$F$4*((R5-MIN($R$4:$R$6))/(MAX($R$4:$R$6)-MIN($R$4:$R$6)))+Inputs!$F$5*((O5-MIN($O$4:$O$6))/(MAX($O$4:$O$6)-MIN($O$4:$O$6)))+Inputs!$F$6*((MAX($B$4:$B$6)-B5)/(MAX($B$4:$B$6)-MIN($B$4:$B$6)))+Inputs!$F$7*((D5-MIN($D$4:$D$6))/(MAX($D$4:$D$6)-MIN($D$4:$D$6)))+Inputs!$F$8*((MAX($E$4:$E$6)-E5)/(MAX($E$4:$E$6)-MIN($E$4:$E$6)))+Inputs!$F$9*((C5-MIN($C$4:$C$6))/(MAX($C$4:$C$6)-MIN($C$4:$C$6)))) -> 49.611604
A6: SouthSide | B6: 11500 | C6: 87000 | D6: 21000 | E6: 10 | F6: 170000 | G6: 23 | H6: 0.59 | I6: 0.008 | J6: 33000 | K6: 9500 | L6: 4500 | M6: =1/(1+E6*Inputs!$B$7) -> 0.625 | N6: =(C6*Inputs!$B$5 + D6*30*I6*Inputs!$B$6)*M6 -> 5257.5 | O6: =N6*G6 -> 120922.5 | P6: =O6*H6 -> 71344.275 | Q6: =B6+J6+K6+L6 -> 58500 | R6: =P6-Q6 -> 12844.275 | S6: =R6*12 -> 154131.3 | T6: =-F6+S6/(1+Inputs!$B$4)+S6/(1+Inputs!$B$4)^2+S6/(1+Inputs!$B$4)^3 -> 213301.73 | U6: =100*(Inputs!$F$4*((R6-MIN($R$4:$R$6))/(MAX($R$4:$R$6)-MIN($R$4:$R$6)))+Inputs!$F$5*((O6-MIN($O$4:$O$6))/(MAX($O$4:$O$6)-MIN($O$4:$O$6)))+Inputs!$F$6*((MAX($B$4:$B$6)-B6)/(MAX($B$4:$B$6)-MIN($B$4:$B$6)))+Inputs!$F$7*((D6-MIN($D$4:$D$6))/(MAX($D$4:$D$6)-MIN($D$4:$D$6)))+Inputs!$F$8*((MAX($E$4:$E$6)-E6)/(MAX($E$4:$E$6)-MIN($E$4:$E$6)))+Inputs!$F$9*((C6-MIN($C$4:$C$6))/(MAX($C$4:$C$6)-MIN($C$4:$C$6)))) -> 79
A9: Decision Support Summary
A10: Best location by 3-year NPV | B10: =INDEX($A$4:$A$6,MATCH(MAX($T$4:$T$6),$T$4:$T$6,0)) -> SouthSide
A11: Best location by weighted score | B11: =INDEX($A$4:$A$6,MATCH(MAX($U$4:$U$6),$U$4:$U$6,0)) -> SouthSide
A12: Highest expected monthly profit | B12: =INDEX($A$4:$A$6,MATCH(MAX($R$4:$R$6),$R$4:$R$6,0)) -> SouthSide
A13: Lowest monthly rent | B13: =INDEX($A$4:$A$6,MATCH(MIN($B$4:$B$6),$B$4:$B$6,0)) -> SouthSide
A14: Recommendation | B14: SouthSide
A15: Rationale | B15: It has the strongest expected profit, the highest 3-year NPV, and the most favorable balance of rent, demand, and operating cost.
A16: Decision caveat | B16: Projected demand should be validated with actual footfall data, lease terms, and a pilot marketing test.

Sheet Scenario_Manager
A1: Scenario Manager / What-If Analysis for Recommended Location (SouthSide)
A3: Selected scenario | B3: Expected Case
A5: Scenario | B5: Traffic Multiplier | C5: Conversion Multiplier | D5: Rent Increase | E5: Competition Change | F5: Marketing Multiplier | G5: Margin Change | H5: Assumption Summary
A6: Best Case | B6: 1.15 | C6: 1.12 | D6: 0 | E6: -1 | F6: 1.1 | G6: 0.02 | H6: Foot traffic and conversion outperform plan; one fewer effective competitor; marketing is scaled modestly.
A7: Expected Case | B7: 1 | C7: 1 | D7: 0 | E7: 0 | F7: 1 | G7: 0 | H7: Base case using the location-comparison assumptions.
A8: Worst Case | B8: 0.85 | C8: 0.88 | D8: 0.07 | E8: 2 | F8: 0.9 | G8: -0.03 | H8: Traffic and conversion underperform; rent escalates; two competitors intensify; margin compresses.
A10: Selected Scenario Outputs | E10: Scenario Comparison Output Table
A11: Metric | B11: Formula / Source | C11: Value | E11: Scenario | F11: Monthly Revenue | G11: Monthly Profit | H11: Annual Profit | I11: 3-Year NPV
A12: Projected Customers | B12: Demand formula adjusted by scenario | C12: =((Location_Data!C6*Inputs!$B$5 + Location_Data!D6*INDEX($B$6:$B$8,MATCH($B$3,$A$6:$A$8,0))*30*Location_Data!I6*Inputs!$B$6*INDEX($C$6:$C$8,MATCH($B$3,$A$6:$A$8,0)))/(1+(Location_Data!E6+INDEX($E$6:$E$8,MATCH($B$3,$A$6:$A$8,0)))*Inputs!$B$7)) -> 5257.5 | E12: Best Case | F12: =((Location_Data!C6*Inputs!$B$5 + Location_Data!D6*B6*30*Location_Data!I6*Inputs!$B$6*C6)/(1+(Location_Data!E6+E6)*Inputs!$B$7))*Location_Data!G6 -> 160319.44 | G12: =((((Location_Data!C6*Inputs!$B$5 + Location_Data!D6*B6*30*Location_Data!I6*Inputs!$B$6*C6)/(1+(Location_Data!E6+E6)*Inputs!$B$7))*Location_Data!G6)*(Location_Data!H6+G6))-(Location_Data!B6*(1+D6)+Location_Data!J6+Location_Data!K6+Location_Data!L6*F6) -> 38844.858 | H12: =G12*12 -> 466138.29 | I12: =-Location_Data!F6+H12/(1+Inputs!$B$4)+H12/(1+Inputs!$B$4)^2+H12/(1+Inputs!$B$4)^3 -> 989216.94
A13: Monthly Revenue | B13: Customers x Avg Ticket | C13: =C12*Location_Data!G6 -> 120922.5 | E13: Expected Case | F13: =((Location_Data!C6*Inputs!$B$5 + Location_Data!D6*B7*30*Location_Data!I6*Inputs!$B$6*C7)/(1+(Location_Data!E6+E7)*Inputs!$B$7))*Location_Data!G6 -> 120922.5 | G13: =((((Location_Data!C6*Inputs!$B$5 + Location_Data!D6*B7*30*Location_Data!I6*Inputs!$B$6*C7)/(1+(Location_Data!E6+E7)*Inputs!$B$7))*Location_Data!G6)*(Location_Data!H6+G7))-(Location_Data!B6*(1+D7)+Location_Data!J6+Location_Data!K6+Location_Data!L6*F7) -> 12844.275 | H13: =G13*12 -> 154131.3 | I13: =-Location_Data!F6+H13/(1+Inputs!$B$4)+H13/(1+Inputs!$B$4)^2+H13/(1+Inputs!$B$4)^3 -> 213301.73
A14: Gross Margin | B14: Base margin + scenario change | C14: =Location_Data!H6+INDEX($G$6:$G$8,MATCH($B$3,$A$6:$A$8,0)) -> 0.59 | E14: Worst Case | F14: =((Location_Data!C6*Inputs!$B$5 + Location_Data!D6*B8*30*Location_Data!I6*Inputs!$B$6*C8)/(1+(Location_Data!E6+E8)*Inputs!$B$7))*Location_Data!G6 -> 85312.242 | G14: =((((Location_Data!C6*Inputs!$B$5 + Location_Data!D6*B8*30*Location_Data!I6*Inputs!$B$6*C8)/(1+(Location_Data!E6+E8)*Inputs!$B$7))*Location_Data!G6)*(Location_Data!H6+G8))-(Location_Data!B6*(1+D8)+Location_Data!J6+Location_Data!K6+Location_Data!L6*F8) -> -11080.145 | H14: =G14*12 -> -132961.73 | I14: =-Location_Data!F6+H14/(1+Inputs!$B$4)+H14/(1+Inputs!$B$4)^2+H14/(1+Inputs!$B$4)^3 -> -500656.15
A15: Monthly Gross Profit | B15: Revenue x gross margin | C15: =C13*C14 -> 71344.275
A16: Monthly Operating Cost | B16: Rent, staffing, fixed, marketing | C16: =Location_Data!B6*(1+INDEX($D$6:$D$8,MATCH($B$3,$A$6:$A$8,0)))+Location_Data!J6+Location_Data!K6+Location_Data!L6*INDEX($F$6:$F$8,MATCH($B$3,$A$6:$A$8,0)) -> 58500
A17: Monthly Profit | B17: Gross profit - operating cost | C17: =C15-C16 -> 12844.275
A18: Annual Profit | B18: Monthly profit x 12 | C18: =C17*12 -> 154131.3
A19: 3-Year NPV | B19: Opening cost + discounted annual profit | C19: =-Location_Data!F6+C18/(1+Inputs!$B$4)+C18/(1+Inputs!$B$4)^2+C18/(1+Inputs!$B$4)^3 -> 213301.73
A22: Excel Scenario Manager setup used
A23: Changing cells | B23: B6:G8 and selected scenario B3
A24: Result cells | B24: C12:C19 and E11:I14
A25: Purpose | B25: Compare Best, Expected, and Worst outcomes for the recommended location using explicit scenario assumptions.

Sheet Goal_Seek_Solver
A1: Goal Seek / Solver Model
A3: Recommended location | B3: SouthSide
A5: Goal Seek: Monthly Revenue Needed for Break-Even NPV | E5: Solver-Style Staffing Optimization
A6: Metric | B6: Formula | C6: Value | E6: Decision variable / metric | F6: Formula / Constraint | G6: Value | H6: Decision
A7: Opening cost | B7: SouthSide opening cost | C7: =Location_Data!F6 -> 170000 | E7: Projected monthly customers | F7: Location_Data!N6 | G7: =Location_Data!N6 -> 5257.5
A8: Discount annuity factor | B8: SUM of years 1-3 at discount rate | C8: =1/(1+Inputs!$B$4)+1/(1+Inputs!$B$4)^2+1/(1+Inputs!$B$4)^3 -> 2.486852 | E8: Service capacity per employee | F8: Inputs!B9 | G8: =Inputs!$B$9 -> 250
A9: Required annual profit for NPV = 0 | B9: Opening cost / annuity factor | C9: =C7/C8 -> 68359.517 | E9: Monthly cost per employee | F9: Inputs!B10 | G9: =Inputs!$B$10 -> 1500
A10: Required monthly profit | B10: Required annual profit / 12 | C10: =C9/12 -> 5696.6264 | E10: Minimum employees required | F10: CEILING(customers / capacity) | G10: =CEILING(G7/G8,1) -> 22
A11: Operating cost | B11: Expected monthly operating cost | C11: =Location_Data!Q6 -> 58500 | E11: Candidate employees | F11: Decision variable | G11: 24
A12: Gross margin | B12: Expected gross margin | C12: =Location_Data!H6 -> 0.59 | E12: Capacity with candidate employees | F12: Candidate x capacity | G12: =G11*G8 -> 6000
A13: Revenue needed for break-even NPV | B13: (Operating cost + required profit) / margin | C13: =(C11+C10)/C12 -> 108807.84 | E13: Capacity constraint | F13: Capacity >= customers | G13: =IF(G12>=G7,"Feasible","Not feasible") -> Feasible
E14: Profit with candidate employees | F14: Gross profit - rent - fixed - marketing - employee cost | G14: =Location_Data!P6-Location_Data!B6-Location_Data!K6-Location_Data!L6-G11*G9 -> 9844.275
E15: Optimal employee count | F15: Minimum employees that satisfies capacity | G15: =G10 -> 22 | H15: Use this staffing level
E16: Optimized monthly profit | F16: Profit at optimal employees | G16: =Location_Data!P6-Location_Data!B6-Location_Data!K6-Location_Data!L6-G15*G9 -> 12844.275
A19: Solver setup documentation
A20: Objective | B20: Maximize optimized monthly profit (G16)
A21: Variable cell | B21: Employee count (G15 or candidate G11)
A22: Constraints | B22: Employees must be whole numbers; capacity must meet or exceed projected monthly customers; employee count between 18 and 36.
A23: Conclusion | B23: The model chooses the lowest feasible employee count because every additional employee increases labor cost once demand is fixed.

Sheet Dashboard
A1: Executive Dashboard: New Store Location DSS
A3: KPI | B3: Value | C3: Interpretation
A4: Recommended location | B4: =Location_Data!B14 -> SouthSide | C4: Chosen by NPV, profitability, and balanced score
A5: Expected monthly profit | B5: =Location_Data!R6 -> 12844.275 | C5: SouthSide expected monthly profit
A6: 3-year NPV | B6: =Location_Data!T6 -> 213301.73 | C6: Value creation after opening cost
A7: Weighted decision score | B7: =Location_Data!U6 -> 79 | C7: Composite score across decision variables
A8: Break-even revenue target | B8: =Goal_Seek_Solver!C13 -> 108807.84 | C8: Goal Seek result for NPV = 0
A10: Scenario | B10: Monthly Profit | C10: 3-Year NPV
A11: Best Case | B11: =Scenario_Manager!G12 -> 38844.858 | C11: =Scenario_Manager!I12 -> 989216.94
A12: Expected Case | B12: =Scenario_Manager!G13 -> 12844.275 | C12: =Scenario_Manager!I13 -> 213301.73
A13: Worst Case | B13: =Scenario_Manager!G14 -> -11080.145 | C13: =Scenario_Manager!I14 -> -500656.15
A14: Decision rule | B14: Proceed if Expected NPV is positive and Worst Case is manageable
