Workbook

Sheet Raw Data
A1: Date | B1: Region | C1: Product ID | D1: Product Name | E1: Salesperson | F1: Quantity | G1: Revenue | H1: Cost | I1: Customer Type | J1: Product Category | K1: Regional Manager | L1: Commission Rate | M1: Gross Profit | N1: High Value Flag | O1: Profitability Flag | P1: Month | Q1: Commission
A2: 45659 | B2: East | C2: P-1003 | D2: Ergonomic Office Chair | E2: Sophia Martinez | F2: 3 | G2: 749.97 | H2: 435 | I2: Retail | J2: =VLOOKUP(C2,'Lookup Tables'!$A$2:$D$11,3,FALSE) -> Office Furniture | K2: =VLOOKUP(B2,'Lookup Tables'!$F$2:$H$5,2,FALSE) -> Amanda Lee | L2: =VLOOKUP(B2,'Lookup Tables'!$F$2:$H$5,3,FALSE) -> 0.05 | M2: =G2-H2 -> 314.97 | N2: =IF(G2>1000,"High Value","Standard") -> Standard | O2: =IF(M2/G2<0.25,"Review Margin","Strong Margin") -> Strong Margin | P2: =TEXT(A2,"mmm") -> Jan | Q2: =G2*L2 -> 37.4985
A3: 45660 | B3: East | C3: P-1001 | D3: Wireless Headphones | E3: Liam Wilson | F3: 1 | G3: 79.99 | H3: 42 | I3: Retail | J3: =VLOOKUP(C3,'Lookup Tables'!$A$2:$D$11,3,FALSE) -> Electronics | K3: =VLOOKUP(B3,'Lookup Tables'!$F$2:$H$5,2,FALSE) -> Amanda Lee | L3: =VLOOKUP(B3,'Lookup Tables'!$F$2:$H$5,3,FALSE) -> 0.05 | M3: =G3-H3 -> 37.99 | N3: =IF(G3>1000,"High Value","Standard") -> Standard | O3: =IF(M3/G3<0.25,"Review Margin","Strong Margin") -> Strong Margin | P3: =TEXT(A3,"mmm") -> Jan | Q3: =G3*L3 -> 3.9995
A4: 45661 | B4: West | C4: P-1010 | D4: Insulated Water Bottle | E4: Noah Brown | F4: 4 | G4: 119.96 | H4: 51 | I4: Retail | J4: =VLOOKUP(C4,'Lookup Tables'!$A$2:$D$11,3,FALSE) -> Travel | K4: =VLOOKUP(B4,'Lookup Tables'!$F$2:$H$5,2,FALSE) -> Carlos Rivera | L4: =VLOOKUP(B4,'Lookup Tables'!$F$2:$H$5,3,FALSE) -> 0.055 | M4: =G4-H4 -> 68.96 | N4: =IF(G4>1000,"High Value","Standard") -> Standard | O4: =IF(M4/G4<0.25,"Review Margin","Strong Margin") -> Strong Margin | P4: =TEXT(A4,"mmm") -> Jan | Q4: =G4*L4 -> 6.5978
A5: 45662 | B5: Midwest | C5: P-1007 | D5: Fitness Tracker | E5: Sophia Martinez | F5: 5 | G5: 299.95 | H5: 153.7 | I5: Retail | J5: =VLOOKUP(C5,'Lookup Tables'!$A$2:$D$11,3,FALSE) -> Fitness | K5: =VLOOKUP(B5,'Lookup Tables'!$F$2:$H$5,2,FALSE) -> Priya Shah | L5: =VLOOKUP(B5,'Lookup Tables'!$F$2:$H$5,3,FALSE) -> 0.045 | M5: =G5-H5 -> 146.25 | N5: =IF(G5>1000,"High Value","Standard") -> Standard | O5: =IF(M5/G5<0.25,"Review Margin","Strong Margin") -> Strong Margin | P5: =TEXT(A5,"mmm") -> Jan | Q5: =G5*L5 -> 13.49775
A6: 45662 | B6: East | C6: P-1002 | D6: Smart Home Hub | E6: Benjamin Moore | F6: 12 | G6: 1439.88 | H6: 822 | I6: Retail | J6: =VLOOKUP(C6,'Lookup Tables'!$A$2:$D$11,3,FALSE) -> Electronics | K6: =VLOOKUP(B6,'Lookup Tables'!$F$2:$H$5,2,FALSE) -> Amanda Lee | L6: =VLOOKUP(B6,'Lookup Tables'!$F$2:$H$5,3,FALSE) -> 0.05 | M6: =G6-H6 -> 617.88 | N6: =IF(G6>1000,"High Value","Standard") -> High Value | O6: =IF(M6/G6<0.25,"Review Margin","Strong Margin") -> Strong Margin | P6: =TEXT(A6,"mmm") -> Jan | Q6: =G6*L6 -> 71.994
A7: 45663 | B7: East | C7: P-1006 | D7: Air Fryer XL | E7: Mia Thomas | F7: 4 | G7: 559.96 | H7: 305.88 | I7: Retail | J7: =VLOOKUP(C7,'Lookup Tables'!$A$2:$D$11,3,FALSE) -> Home Goods | K7: =VLOOKUP(B7,'Lookup Tables'!$F$2:$H$5,2,FALSE) -> Amanda Lee | L7: =VLOOKUP(B7,'Lookup Tables'!$F$2:$H$5,3,FALSE) -> 0.05 | M7: =G7-H7 -> 254.08 | N7: =IF(G7>1000,"High Value","Standard") -> Standard | O7: =IF(M7/G7<0.25,"Review Margin","Strong Margin") -> Strong Margin | P7: =TEXT(A7,"mmm") -> Jan | Q7: =G7*L7 -> 27.998
A8: 45666 | B8: East | C8: P-1004 | D8: Standing Desk Converter | E8: Maya Johnson | F8: 9 | G8: 1709.91 | H8: 992.25 | I8: Retail | J8: =VLOOKUP(C8,'Lookup Tables'!$A$2:$D$11,3,FALSE) -> Office Furniture | K8: =VLOOKUP(B8,'Lookup Tables'!$F$2:$H$5,2,FALSE) -> Amanda Lee | L8: =VLOOKUP(B8,'Lookup Tables'!$F$2:$H$5,3,FALSE) -> 0.05 | M8: =G8-H8 -> 717.66 | N8: =IF(G8>1000,"High Value","Standard") -> High Value | O8: =IF(M8/G8<0.25,"Review Margin","Strong Margin") -> Strong Margin | P8: =TEXT(A8,"mmm") -> Jan | Q8: =G8*L8 -> 85.4955
A9: 45667 | B9: Midwest | C9: P-1004 | D9: Standing Desk Converter | E9: Benjamin Moore | F9: 4 | G9: 759.96 | H9: 441 | I9: Retail | J9: =VLOOKUP(C9,'Lookup Tables'!$A$2:$D$11,3,FALSE) -> Office Furniture | K9: =VLOOKUP(B9,'Lookup Tables'!$F$2:$H$5,2,FALSE) -> Priya Shah | L9: =VLOOKUP(B9,'Lookup Tables'!$F$2:$H$5,3,FALSE) -> 0.045 | M9: =G9-H9 -> 318.96 | N9: =IF(G9>1000,"High Value","Standard") -> Standard | O9: =IF(M9/G9<0.25,"Review Margin","Strong Margin") -> Strong Margin | P9: =TEXT(A9,"mmm") -> Jan | Q9: =G9*L9 -> 34.1982
A10: 45668 | B10: East | C10: P-1007 | D10: Fitness Tracker | E10: Ethan Smith | F10: 18 | G10: 842.26 | H10: 553.32 | I10: Wholesale | J10: =VLOOKUP(C10,'Lookup Tables'!$A$2:$D$11,3,FALSE) -> Fitness | K10: =VLOOKUP(B10,'Lookup Tables'!$F$2:$H$5,2,FALSE) -> Amanda Lee | L10: =VLOOKUP(B10,'Lookup Tables'!$F$2:$H$5,3,FALSE) -> 0.05 | M10: =G10-H10 -> 288.94 | N10: =IF(G10>1000,"High Value","Standard") -> Standard | O10: =IF(M10/G10<0.25,"Review Margin","Strong Margin") -> Strong Margin | P10: =TEXT(A10,"mmm") -> Jan | Q10: =G10*L10 -> 42.113
A11: 45669 | B11: West | C11: P-1008 | D11: Yoga Starter Kit | E11: Ava Davis | F11: 12 | G11: 599.88 | H11: 299.4 | I11: Retail | J11: =VLOOKUP(C11,'Lookup Tables'!$A$2:$D$11,3,FALSE) -> Fitness | K11: =VLOOKUP(B11,'Lookup Tables'!$F$2:$H$5,2,FALSE) -> Carlos Rivera | L11: =VLOOKUP(B11,'Lookup Tables'!$F$2:$H$5,3,FALSE) -> 0.055 | M11: =G11-H11 -> 300.48 | N11: =IF(G11>1000,"High Value","Standard") -> Standard | O11: =IF(M11/G11<0.25,"Review Margin","Strong Margin") -> Strong Margin | P11: =TEXT(A11,"mmm") -> Jan | Q11: =G11*L11 -> 32.9934
A12: 45670 | B12: Midwest | C12: P-1005 | D12: Stainless Cookware Set | E12: Noah Brown | F12: 11 | G12: 1372.71 | H12: 1036.2 | I12: Wholesale | J12: =VLOOKUP(C12,'Lookup Tables'!$A$2:$D$11,3,FALSE) -> Home Goods | K12: =VLOOKUP(B12,'Lookup Tables'!$F$2:$H$5,2,FALSE) -> Priya Shah | L12: =VLOOKUP(B12,'Lookup Tables'!$F$2:$H$5,3,FALSE) -> 0.045 | M12: =G12-H12 -> 336.51 | N12: =IF(G12>1000,"High Value","Standard") -> High Value | O12: =IF(M12/G12<0.25,"Review Margin","Strong Margin") -> Review Margin | P12: =TEXT(A12,"mmm") -> Jan | Q12: =G12*L12 -> 61.77195
A13: 45670 | B13: Midwest | C13: P-1009 | D13: Travel Backpack | E13: Mia Thomas | F13: 1 | G13: 89.99 | H13: 51.83 | I13: Retail | J13: =VLOOKUP(C13,'Lookup Tables'!$A$2:$D$11,3,FALSE) -> Travel | K13: =VLOOKUP(B13,'Lookup Tables'!$F$2:$H$5,2,FALSE) -> Priya Shah | L13: =VLOOKUP(B13,'Lookup Tables'!$F$2:$H$5,3,FALSE) -> 0.045 | M13: =G13-H13 -> 38.16 | N13: =IF(G13>1000,"High Value","Standard") -> Standard | O13: =IF(M13/G13<0.25,"Review Margin","Strong Margin") -> Strong Margin | P13: =TEXT(A13,"mmm") -> Jan | Q13: =G13*L13 -> 4.04955
... A241: 45909 | B241: East | C241: P-1002 | D241: Smart Home Hub | E241: Benjamin Moore | F241: 5 | G241: 599.95 | H241: 342.5 | I241: Retail | J241: =VLOOKUP(C241,'Lookup Tables'!$A$2:$D$11,3,FALSE) -> Electronics | K241: =VLOOKUP(B241,'Lookup Tables'!$F$2:$H$5,2,FALSE) -> Amanda Lee | L241: =VLOOKUP(B241,'Lookup Tables'!$F$2:$H$5,3,FALSE) -> 0.05 | M241: =G241-H241 -> 257.45 | N241: =IF(G241>1000,"High Value","Standard") -> Standard | O241: =IF(M241/G241<0.25,"Review Margin","Strong Margin") -> Strong Margin | P241: =TEXT(A241,"mmm") -> Sep | Q241: =G241*L241 -> 29.9975

Sheet Lookup Tables
A1: Product ID | B1: Product Name | C1: Category | D1: Unit Price | F1: Region | G1: Regional Manager | H1: Commission Rate
A2: P-1001 | B2: Wireless Headphones | C2: Electronics | D2: 79.99 | F2: East | G2: Amanda Lee | H2: 0.05
A3: P-1002 | B3: Smart Home Hub | C3: Electronics | D3: 119.99 | F3: West | G3: Carlos Rivera | H3: 0.055
A4: P-1003 | B4: Ergonomic Office Chair | C4: Office Furniture | D4: 249.99 | F4: Midwest | G4: Priya Shah | H4: 0.045
A5: P-1004 | B5: Standing Desk Converter | C5: Office Furniture | D5: 189.99 | F5: South | G5: Marcus Green | H5: 0.05
A6: P-1005 | B6: Stainless Cookware Set | C6: Home Goods | D6: 159.99
A7: P-1006 | B7: Air Fryer XL | C7: Home Goods | D7: 139.99
A8: P-1007 | B8: Fitness Tracker | C8: Fitness | D8: 59.99
A9: P-1008 | B9: Yoga Starter Kit | C9: Fitness | D9: 49.99
A10: P-1009 | B10: Travel Backpack | C10: Travel | D10: 89.99
A11: P-1010 | B11: Insulated Water Bottle | C11: Travel | D11: 29.99

Sheet Calculations
A1: Made by Juan Barrera
A2: Professor Jeffrey Seaman
A3: Management Information Systems
A5: Revenue by Region | D5: Revenue by Product | G5: Revenue by Salesperson | J5: Monthly Sales Trend | N5: Customer Type Analysis
A6: Region | B6: Revenue | D6: Product Name | E6: Revenue | G6: Salesperson | H6: Revenue | J6: Month | K6: Revenue | L6: Quantity | N6: Customer Type | O6: Revenue | P6: Quantity
A7: East | B7: =SUMIFS('Raw Data'!$G:$G,'Raw Data'!$B:$B,A7) -> 75143.08 | D7: Wireless Headphones | E7: =SUMIFS('Raw Data'!$G:$G,'Raw Data'!$D:$D,D7) -> 10883.43 | G7: Ava Davis | H7: =SUMIFS('Raw Data'!$G:$G,'Raw Data'!$E:$E,G7) -> 17660.74 | J7: Jan | K7: =SUMIFS('Raw Data'!$G:$G,'Raw Data'!$P:$P,J7) -> 23446.41 | L7: =SUMIFS('Raw Data'!$F:$F,'Raw Data'!$P:$P,J7) -> 237 | N7: Retail | O7: =SUMIFS('Raw Data'!$G:$G,'Raw Data'!$I:$I,N7) -> 125069.17 | P7: =SUMIFS('Raw Data'!$F:$F,'Raw Data'!$I:$I,N7) -> 1083
A8: West | B8: =SUMIFS('Raw Data'!$G:$G,'Raw Data'!$B:$B,A8) -> 73820.27 | D8: Smart Home Hub | E8: =SUMIFS('Raw Data'!$G:$G,'Raw Data'!$D:$D,D8) -> 28603.21 | G8: Noah Brown | H8: =SUMIFS('Raw Data'!$G:$G,'Raw Data'!$E:$E,G8) -> 31621.79 | J8: Feb | K8: =SUMIFS('Raw Data'!$G:$G,'Raw Data'!$P:$P,J8) -> 25965.33 | L8: =SUMIFS('Raw Data'!$F:$F,'Raw Data'!$P:$P,J8) -> 304 | N8: Wholesale | O8: =SUMIFS('Raw Data'!$G:$G,'Raw Data'!$I:$I,N8) -> 114438.8 | P8: =SUMIFS('Raw Data'!$F:$F,'Raw Data'!$I:$I,N8) -> 1361
A9: Midwest | B9: =SUMIFS('Raw Data'!$G:$G,'Raw Data'!$B:$B,A9) -> 48392.96 | D9: Ergonomic Office Chair | E9: =SUMIFS('Raw Data'!$G:$G,'Raw Data'!$D:$D,D9) -> 40103.4 | G9: Sophia Martinez | H9: =SUMIFS('Raw Data'!$G:$G,'Raw Data'!$E:$E,G9) -> 24102.37 | J9: Mar | K9: =SUMIFS('Raw Data'!$G:$G,'Raw Data'!$P:$P,J9) -> 25191.54 | L9: =SUMIFS('Raw Data'!$F:$F,'Raw Data'!$P:$P,J9) -> 286
A10: South | B10: =SUMIFS('Raw Data'!$G:$G,'Raw Data'!$B:$B,A10) -> 42151.66 | D10: Standing Desk Converter | E10: =SUMIFS('Raw Data'!$G:$G,'Raw Data'!$D:$D,D10) -> 31808.13 | G10: Liam Wilson | H10: =SUMIFS('Raw Data'!$G:$G,'Raw Data'!$E:$E,G10) -> 22400.77 | J10: Apr | K10: =SUMIFS('Raw Data'!$G:$G,'Raw Data'!$P:$P,J10) -> 40237.13 | L10: =SUMIFS('Raw Data'!$F:$F,'Raw Data'!$P:$P,J10) -> 401
D11: Stainless Cookware Set | E11: =SUMIFS('Raw Data'!$G:$G,'Raw Data'!$D:$D,D11) -> 43446.9 | G11: Mia Thomas | H11: =SUMIFS('Raw Data'!$G:$G,'Raw Data'!$E:$E,G11) -> 24945.83 | J11: May | K11: =SUMIFS('Raw Data'!$G:$G,'Raw Data'!$P:$P,J11) -> 31496.65 | L11: =SUMIFS('Raw Data'!$F:$F,'Raw Data'!$P:$P,J11) -> 353
D12: Air Fryer XL | E12: =SUMIFS('Raw Data'!$G:$G,'Raw Data'!$D:$D,D12) -> 27779.62 | G12: Ethan Smith | H12: =SUMIFS('Raw Data'!$G:$G,'Raw Data'!$E:$E,G12) -> 16380.53 | J12: Jun | K12: =SUMIFS('Raw Data'!$G:$G,'Raw Data'!$P:$P,J12) -> 32201.38 | L12: =SUMIFS('Raw Data'!$F:$F,'Raw Data'!$P:$P,J12) -> 317
D13: Fitness Tracker | E13: =SUMIFS('Raw Data'!$G:$G,'Raw Data'!$D:$D,D13) -> 15619 | G13: Olivia Garcia | H13: =SUMIFS('Raw Data'!$G:$G,'Raw Data'!$E:$E,G13) -> 27889.71 | J13: Jul | K13: =SUMIFS('Raw Data'!$G:$G,'Raw Data'!$P:$P,J13) -> 21686.02 | L13: =SUMIFS('Raw Data'!$F:$F,'Raw Data'!$P:$P,J13) -> 204
D14: Yoga Starter Kit | E14: =SUMIFS('Raw Data'!$G:$G,'Raw Data'!$D:$D,D14) -> 11125.77 | G14: Benjamin Moore | H14: =SUMIFS('Raw Data'!$G:$G,'Raw Data'!$E:$E,G14) -> 33190.54 | J14: Aug | K14: =SUMIFS('Raw Data'!$G:$G,'Raw Data'!$P:$P,J14) -> 28548.48 | L14: =SUMIFS('Raw Data'!$F:$F,'Raw Data'!$P:$P,J14) -> 260
D15: Travel Backpack | E15: =SUMIFS('Raw Data'!$G:$G,'Raw Data'!$D:$D,D15) -> 23190.43 | G15: Maya Johnson | H15: =SUMIFS('Raw Data'!$G:$G,'Raw Data'!$E:$E,G15) -> 19519.78 | J15: Sep | K15: =SUMIFS('Raw Data'!$G:$G,'Raw Data'!$P:$P,J15) -> 10735.03 | L15: =SUMIFS('Raw Data'!$F:$F,'Raw Data'!$P:$P,J15) -> 82
D16: Insulated Water Bottle | E16: =SUMIFS('Raw Data'!$G:$G,'Raw Data'!$D:$D,D16) -> 6948.08 | G16: James Anderson | H16: =SUMIFS('Raw Data'!$G:$G,'Raw Data'!$E:$E,G16) -> 21795.91

Sheet Dashboard
A1: Keystone Retail Solutions - Executive Sales Dashboard
A2: Made by Juan Barrera | Professor Jeffrey Seaman | Management Information Systems
A4: KPI | B4: Value | D4: Revenue by Region | E4: Revenue | G4: Salesperson Performance | H4: Revenue
A5: Total Revenue | B5: =SUM('Raw Data'!$G:$G) -> 239507.97 | D5: =Calculations!A7 -> East | E5: =Calculations!B7 -> 75143.08 | G5: =Calculations!G7 -> Ava Davis | H5: =Calculations!H7 -> 17660.74
A6: Total Quantity Sold | B6: =SUM('Raw Data'!$F:$F) -> 2444 | D6: =Calculations!A8 -> West | E6: =Calculations!B8 -> 73820.27 | G6: =Calculations!G8 -> Noah Brown | H6: =Calculations!H8 -> 31621.79
A7: Average Sale Amount | B7: =AVERAGE('Raw Data'!$G:$G) -> 997.94988 | D7: =Calculations!A9 -> Midwest | E7: =Calculations!B9 -> 48392.96 | G7: =Calculations!G9 -> Sophia Martinez | H7: =Calculations!H9 -> 24102.37
A8: Top Performing Region | B8: =INDEX(Calculations!$A$7:$A$10,MATCH(MAX(Calculations!$B$7:$B$10),Calculations!$B$7:$B$10,0)) -> East | D8: =Calculations!A10 -> South | E8: =Calculations!B10 -> 42151.66 | G8: =Calculations!G10 -> Liam Wilson | H8: =Calculations!H10 -> 22400.77
A9: Top Product | B9: =INDEX(Calculations!$D$7:$D$16,MATCH(MAX(Calculations!$E$7:$E$16),Calculations!$E$7:$E$16,0)) -> Stainless Cookware Set | G9: =Calculations!G11 -> Mia Thomas | H9: =Calculations!H11 -> 24945.83
A10: Top Salesperson | B10: =INDEX(Calculations!$G$7:$G$16,MATCH(MAX(Calculations!$H$7:$H$16),Calculations!$H$7:$H$16,0)) -> Benjamin Moore | G10: =Calculations!G12 -> Ethan Smith | H10: =Calculations!H12 -> 16380.53
G11: =Calculations!G13 -> Olivia Garcia | H11: =Calculations!H13 -> 27889.71
G12: =Calculations!G14 -> Benjamin Moore | H12: =Calculations!H14 -> 33190.54
A13: Monthly Sales Trend | B13: Revenue | D13: Top Products | E13: Revenue | G13: =Calculations!G15 -> Maya Johnson | H13: =Calculations!H15 -> 19519.78
A14: =Calculations!J7 -> Jan | B14: =Calculations!K7 -> 23446.41 | D14: =Calculations!D7 -> Wireless Headphones | E14: =Calculations!E7 -> 10883.43 | G14: =Calculations!G16 -> James Anderson | H14: =Calculations!H16 -> 21795.91
A15: =Calculations!J8 -> Feb | B15: =Calculations!K8 -> 25965.33 | D15: =Calculations!D8 -> Smart Home Hub | E15: =Calculations!E8 -> 28603.21
A16: =Calculations!J9 -> Mar | B16: =Calculations!K9 -> 25191.54 | D16: =Calculations!D9 -> Ergonomic Office Chair | E16: =Calculations!E9 -> 40103.4
A17: =Calculations!J10 -> Apr | B17: =Calculations!K10 -> 40237.13 | D17: =Calculations!D10 -> Standing Desk Converter | E17: =Calculations!E10 -> 31808.13 | G17: Customer Type | H17: Revenue
A18: =Calculations!J11 -> May | B18: =Calculations!K11 -> 31496.65 | D18: =Calculations!D11 -> Stainless Cookware Set | E18: =Calculations!E11 -> 43446.9 | G18: =Calculations!N7 -> Retail | H18: =Calculations!O7 -> 125069.17
A19: =Calculations!J12 -> Jun | B19: =Calculations!K12 -> 32201.38 | D19: =Calculations!D12 -> Air Fryer XL | E19: =Calculations!E12 -> 27779.62 | G19: =Calculations!N8 -> Wholesale | H19: =Calculations!O8 -> 114438.8
A20: =Calculations!J13 -> Jul | B20: =Calculations!K13 -> 21686.02 | D20: =Calculations!D13 -> Fitness Tracker | E20: =Calculations!E13 -> 15619
A21: =Calculations!J14 -> Aug | B21: =Calculations!K14 -> 28548.48 | D21: =Calculations!D14 -> Yoga Starter Kit | E21: =Calculations!E14 -> 11125.77
A22: =Calculations!J15 -> Sep | B22: =Calculations!K15 -> 10735.03 | D22: =Calculations!D15 -> Travel Backpack | E22: =Calculations!E15 -> 23190.43
D23: =Calculations!D16 -> Insulated Water Bottle | E23: =Calculations!E16 -> 6948.08
A25: Executive Insights
A26: The dashboard highlights total revenue, quantity sold, average sale amount, and top performers. Leadership should focus on the strongest region and product categories while reviewing the lowest-performing region for sales support, inventory placement, and marketing opportunities.
